Metadata-Version: 2.1
Name: pulumi-postgresql-exec
Version: 0.1.0
Summary: A Pulumi package for executing arbitrary SQL queries against a PostgreSQL database.
Home-page: UNKNOWN
License: Apache-2.0
Project-URL: Repository, https://github.com/benesch/pulumi-postgresql-exec
Platform: UNKNOWN
